LICENSE
MANIFEST.in
README.md
setup.py
grpcurl_binary_wrapper/__init__.py
grpcurl_binary_wrapper.egg-info/PKG-INFO
grpcurl_binary_wrapper.egg-info/SOURCES.txt
grpcurl_binary_wrapper.egg-info/dependency_links.txt
grpcurl_binary_wrapper.egg-info/entry_points.txt
grpcurl_binary_wrapper.egg-info/top_level.txt
grpcurl_binary_wrapper/lib/__init__.py
grpcurl_binary_wrapper/lib/grpcurl