Metadata-Version: 1.0
Name: grpcurl-binary-wrapper
Version: 1.8.6.post2
Summary: Python wrapper for Grpcurl
Home-page: https://github.com/taheri1395/grpcurl-binary-wrapper
Author: Amirhossein Taheri
Author-email: taheri@mahsan.co
License: UNKNOWN
Platform: UNKNOWN
